countdowntimer/__init__.py
simple_countdowntimer-0.0.2.dist-info/LICENCE.txt
simple_countdowntimer-0.0.2.dist-info/METADATA
simple_countdowntimer-0.0.2.dist-info/WHEEL
simple_countdowntimer-0.0.2.dist-info/top_level.txt
simple_countdowntimer-0.0.2.dist-info/RECORD
