Metadata-Version: 2.1
Name: simple-countdowntimer
Version: 0.0.2
Summary: A simple countdown timer library for Python or MicroPython
Author-email: Kevin McAleer <kevinmcaleer@gmail.com>
Project-URL: Homepage, https://github.com/kevinmcaleer/countdowntimer
Project-URL: Bug Tracker, https://github.com/kevinmcaleer/countdowntimer/issues
Classifier: Programming Language :: Python :: 3
Classifier: License :: OSI Approved :: MIT License
Classifier: Operating System :: OS Independent
Requires-Python: >=3.7
License-File: LICENCE.txt
